{
  "course_id": 2,
  "name": "기초",
  "description": "그리스도인의 생활 8구절",
  "total_verses": 8,
  "verses": [
    {
      "order_num": 1,
      "reference": "요15:5",
      "text": "나는 포도나무요 너희는 가지니 저가 내 안에 내가 저 안에 있으면 이 사람은 과실을 많이 맺나니 나를 떠나서는 너희가 아무것도 할 수 없음이라",
      "text_short": "나는 포도나무요 너희는 가지니 저가 내 안에 내가 저 ...",
      "topic": "그리스도 안의 생활",
      "subtopic": "8구절"
    },
    {
      "order_num": 2,
      "reference": "행20:32",
      "text": "지금 내가 너희를 주와 및 그 은혜의 말씀께 부탁하노니 그 말씀이 너희를 능히 든든히 세우사 거룩케 하심을 입은 모든 자 가운데 기업이 있게 하시리라",
      "text_short": "지금 내가 너희를 주와 및 그 은혜의 말씀께 부탁하노니...",
      "topic": "하나님의 말씀에 의한 생활",
      "subtopic": "8구절"
    },
    {
      "order_num": 3,
      "reference": "롬8:14",
      "text": "무릇 하나님의 영으로 인도함을 받는 그들은 곧 하나님의 아들이라",
      "text_short": "무릇 하나님의 영으로 인도함을 받는 그들은 곧 하나님의...",
      "topic": "하나님의 성령에 의한 생활",
      "subtopic": "8구절"
    },
    {
      "order_num": 4,
      "reference": "고후5:7",
      "text": "이는 우리가 믿음으로 행하고 보는 것으로 하지 아니함이로라",
      "text_short": "이는 우리가 믿음으로 행하고 보는 것으로 하지 아니함이...",
      "topic": "믿음에 의한 생활",
      "subtopic": "8구절"
    },
    {
      "order_num": 5,
      "reference": "요일4:11",
      "text": "사랑하는 자들아 하나님이 이같이 우리를 사랑하셨은즉 우리도 서로 사랑하는 것이 마땅하도다",
      "text_short": "사랑하는 자들아 하나님이 이같이 우리를 사랑하셨은즉 우...",
      "topic": "사랑에 의한 생활",
      "subtopic": "8구절"
    },
    {
      "order_num": 6,
      "reference": "요일1:7",
      "text": "저가 빛 가운데 계신 것같이 우리도 빛 가운데 행하면 우리가 서로 사귐이 있고 그 아들 예수의 피가 우리를 모든 죄에서 깨끗하게 하실 것이요",
      "text_short": "저가 빛 가운데 계신 것같이 우리도 빛 가운데 행하면 ...",
      "topic": "그리스도인의 교제하는 생활",
      "subtopic": "8구절"
    },
    {
      "order_num": 7,
      "reference": "벧전3:15",
      "text": "너희 마음에 그리스도를 주로 삼아 거룩하게 하고 너희 속에 있는 소망에 관한 이유를 묻는 자에게는 대답할 것을 항상 예비하되 온유와 두려움으로 하고",
      "text_short": "너희 마음에 그리스도를 주로 삼아 거룩하게 하고 너희 ...",
      "topic": "증인으로서의 생활",
      "subtopic": "8구절"
    },
    {
      "order_num": 8,
      "reference": "고후9:7",
      "text": "각각 그 마음에 정한 대로 할 것이요 인색함으로나 억지로 하지 말지니 하나님은 즐겨 내는 자를 사랑하시느니라",
      "text_short": "각각 그 마음에 정한 대로 할 것이요 인색함으로나 억지...",
      "topic": "후히 드리는 생활",
      "subtopic": "8구절"
    }
  ]
}